sub3/__init__.py
sub3/main.py
sub3/rpc_maker.py
Sub3-1.0.0.dist-info/AUTHORS.rst
Sub3-1.0.0.dist-info/LICENSE
Sub3-1.0.0.dist-info/METADATA
Sub3-1.0.0.dist-info/WHEEL
Sub3-1.0.0.dist-info/top_level.txt
Sub3-1.0.0.dist-info/RECORD
