Metadata-Version: 2.1
Name: Sub3
Version: 1.0.0
Summary: A Python aiohttp wrapper client to subscribe to the Ethereum JSON-RPC PubSub endpoints.
Home-page: https://github.com/SpeakinTelnet/Sub3
Author: SpeakinTelnet
Author-email: gui.lac@protonmail.com
License: License :: OSI Approved :: MIT License
Keywords: Sub3
Platform: UNKNOWN
Classifier: Development Status :: 2 - Pre-Alpha
Classifier: Intended Audience :: Developers
Classifier: License :: OSI Approved :: MIT License
Classifier: Natural Language :: English
Classifier: Programming Language :: Python :: 3
Classifier: Programming Language :: Python :: 3.10
Requires-Python: >=3.10
License-File: LICENSE
License-File: AUTHORS.rst
Requires-Dist: aiohttp
